candiy/__init__.py
candiy/main.py
candiy/presenter/__init__.py
candiy/presenter/event_manager.py
candiy/presenter/events.py
candiy/presenter/presenter.py
candiy/py.typed
candiy/views/__init__.py
candiy/views/icons.py
candiy/views/main_view.py
candiy/views/resources/Heartbeat_dark_blue_42px.png
candiy/views/resources/Heartbeat_red_42px.png
candiy/views/resources/Lollipop_icon.ico
candiy/views/resources/Lollipop_icon.png
candiy/views/resources/Power_dark_blue_42px.png
candiy/views/resources/Power_green_42px.png
candiy/views/resources/Spy_dark_blue_42px.png
candiy/views/resources/Spy_orange_42px.png
candiy/views/resources/Toggle_off_42px.png
candiy/views/resources/Toggle_on_42px.png
candiy/views/resources/Tools_dark_blue_42px.png
candiy/views/resources/Tools_light_blue_42px.png
candiy/views/view.py
candiy-0.0.2.dist-info/LICENSE
candiy-0.0.2.dist-info/METADATA
candiy-0.0.2.dist-info/WHEEL
candiy-0.0.2.dist-info/RECORD
