Metadata-Version: 2.1
Name: candiy
Version: 0.0.2
Summary: GUI to monitor a CAN network and communicate with an ECU.
Home-page: https://github.com/cuinixam/candiy
License: MIT
Author: cuinixam
Author-email: me@cuinixam.com
Requires-Python: >=3.10,<4.0
Classifier: Development Status :: 2 - Pre-Alpha
Classifier: Intended Audience :: Developers
Classifier: License :: OSI Approved :: MIT License
Classifier: Natural Language :: English
Classifier: Operating System :: OS Independent
Classifier: Programming Language :: Python :: 3
Classifier: Programming Language :: Python :: 3.10
Classifier: Programming Language :: Python :: 3.11
Classifier: Topic :: Software Development :: Libraries
Requires-Dist: customtkinter (>=5.1.2,<6.0.0)
Requires-Dist: pillow (>=9.4.0,<10.0.0)
Project-URL: Bug Tracker, https://github.com/cuinixam/candiy/issues
Project-URL: Changelog, https://github.com/cuinixam/candiy/blob/main/CHANGELOG.md
Project-URL: Documentation, https://candiy.readthedocs.io
Project-URL: Repository, https://github.com/cuinixam/candiy
